cgodme/__init__.py
cgodme/calibration.py
cgodme/config.yaml
cgodme/data.py
cgodme/run.py
cgodme-0.1.4.dist-info/METADATA
cgodme-0.1.4.dist-info/WHEEL
cgodme-0.1.4.dist-info/top_level.txt
cgodme-0.1.4.dist-info/RECORD
