Metadata-Version: 2.1
Name: cgodme
Version: 0.1.4
Summary: Find optimal path flows that map systematic variables (origin-destination demand and link flows) to ensure consistency
Home-page: https://github.com/Taehooie/CGODME
Author: Taehooie Kim, Ph.D., Xin Wu, Ph.D., Han Zheng, Ph.D., Xuesong Zhou, Ph.D.
Author-email: taehooie.kim@gmail.com, xin.wu@villanova.edu, hzheng73@asu.edu, xzhou74@asu.edu
